pywlroots-0.17.0.dist-info/LICENSE
pywlroots-0.17.0.dist-info/METADATA
pywlroots-0.17.0.dist-info/RECORD
pywlroots-0.17.0.dist-info/top_level.txt
pywlroots-0.17.0.dist-info/WHEEL
pywlroots.libs/libxcb-randr-562554c2.so.0.1.0
pywlroots.libs/libgpg-error-d4e115d0.so.0.24.2
pywlroots.libs/libwacom-a563e81a.so.2.6.1
pywlroots.libs/libselinux-64a010fa.so.1
pywlroots.libs/libxcb-composite-84417425.so.0.0.0
pywlroots.libs/libwayland-client-4f0c8158.so.0.22.0
pywlroots.libs/libunistring-05abdd40.so.2.1.0
pywlroots.libs/libxcb-render-161c0eb5.so.0.0.0
pywlroots.libs/libinput-a3c39512.so.10.13.0
pywlroots.libs/libidn2-2f4a5893.so.0.3.6
pywlroots.libs/libgmp-452f15e0.so.10.3.2
pywlroots.libs/libxcb-xfixes-6de855b8.so.0.0.0
pywlroots.libs/libxcb-present-9d0789f6.so.0.0.0
pywlroots.libs/libGLESv2-3f2b8a3d.so.2.1.0
pywlroots.libs/libxcb-5ddf6756.so.1.1.0
pywlroots.libs/libEGL-976e38d5.so.1.1.0
pywlroots.libs/libcap-16fca4d2.so.2.48
pywlroots.libs/libpcre2-8-516f4c9d.so.0.7.1
pywlroots.libs/libxcb-xinput-5c69f591.so.0.1.0
pywlroots.libs/libpcre-0dd207b5.so.1.2.10
pywlroots.libs/libevdev-bed09dca.so.2.3.0
pywlroots.libs/libxcb-shm-0be6dfbf.so.0.0.0
pywlroots.libs/libgcrypt-a1b5cc4c.so.20.2.5
pywlroots.libs/libxcb-res-d1051bd6.so.0.0.0
pywlroots.libs/libxcb-ewmh-dc696952.so.2.0.0
pywlroots.libs/libxcb-icccm-9453e4f7.so.4.0.0
pywlroots.libs/libseat-a44803ed.so.1
pywlroots.libs/libnettle-37944285.so.6.5
pywlroots.libs/liblzma-51a76f52.so.5.2.4
pywlroots.libs/libgmodule-2-b0ca77de.0.so.0.5600.4
pywlroots.libs/libmount-a0fce023.so.1.1.0
pywlroots.libs/libudev-6ca67360.so.1.6.11
pywlroots.libs/libgbm-d69d73a7.so.1.0.0
pywlroots.libs/libpixman-1-af926b34.so.0.42.0
pywlroots.libs/libtasn1-222cca92.so.6.5.5
pywlroots.libs/libhogweed-cd4c53be.so.4.5
pywlroots.libs/liblz4-a5753129.so.1.8.3
pywlroots.libs/libblkid-7ac37cd8.so.1.1.0
pywlroots.libs/libxcb-dri3-74eae955.so.0.0.0
pywlroots.libs/libwayland-server-ba005aa1.so.0.22.0
pywlroots.libs/libsystemd-8bc3ba84.so.0.23.0
pywlroots.libs/libuuid-48d6f845.so.1.3.0
pywlroots.libs/libdrm-6768d3b2.so.2.4.0
pywlroots.libs/libmtdev-95d9e17e.so.1.0.0
