Metadata-Version: 2.1
Name: pywlroots
Version: 0.17.0
Summary: Python binding to the wlroots library using cffi
Author-email: Sean Vig <sean.v.775@gmail.com>
License: University of Illinois/NCSA Open Source License
Project-URL: homepage, https://github.com/flacjacket/pywlroots
Classifier: Development Status :: 2 - Pre-Alpha
Classifier: Operating System :: POSIX
Classifier: Operating System :: POSIX :: Linux
Classifier: Programming Language :: Python :: 3 :: Only
Classifier: Programming Language :: Python :: 3.8
Classifier: Programming Language :: Python :: 3.9
Classifier: Programming Language :: Python :: 3.10
Classifier: Programming Language :: Python :: 3.11
Classifier: Programming Language :: Python :: Implementation :: CPython
Classifier: Programming Language :: Python :: Implementation :: PyPy
Classifier: Topic :: Desktop Environment :: Window Managers
Classifier: Topic :: Software Development :: Libraries
Requires-Python: >=3.8
License-File: LICENSE
Requires-Dist: pywayland >=0.4.14
Requires-Dist: xkbcommon >=0.2
Requires-Dist: cffi >=1.12.0 ; platform_python_implementation != "PyPy"
Provides-Extra: test
Requires-Dist: pytest ; extra == 'test'
Provides-Extra: typecheck
Requires-Dist: mypy ; extra == 'typecheck'
Requires-Dist: types-cffi ; extra == 'typecheck'
Requires-Dist: types-dataclasses ; extra == 'typecheck'
